Ecmascript6Rumen/README.md
Ecmascript6Rumen/__init__.py
Ecmascript6Rumen/__main__.py
Ecmascript6Rumen/file.epub
Ecmascript6Rumen/index.html
Ecmascript6Rumen/css/__init__.py
Ecmascript6Rumen/css/annotations.css
Ecmascript6Rumen/css/main.css
Ecmascript6Rumen/css/normalize.css
Ecmascript6Rumen/css/popup.css
Ecmascript6Rumen/font/__init__.py
Ecmascript6Rumen/font/fontello.eot
Ecmascript6Rumen/font/fontello.svg
Ecmascript6Rumen/font/fontello.ttf
Ecmascript6Rumen/font/fontello.woff
Ecmascript6Rumen/img/__init__.py
Ecmascript6Rumen/img/annotator-glyph-sprite.png
Ecmascript6Rumen/img/annotator-icon-sprite.png
Ecmascript6Rumen/img/apple-touch-icon.png
Ecmascript6Rumen/img/cancelfullscreen.png
Ecmascript6Rumen/img/close.png
Ecmascript6Rumen/img/fullscreen.png
Ecmascript6Rumen/img/loader.gif
Ecmascript6Rumen/img/menu-icon.png
Ecmascript6Rumen/img/save.png
Ecmascript6Rumen/img/saved.png
Ecmascript6Rumen/img/settings-s.png
Ecmascript6Rumen/img/settings.png
Ecmascript6Rumen/img/star.png
Ecmascript6Rumen/js/__init__.py
Ecmascript6Rumen/js/epub.js
Ecmascript6Rumen/js/epub.min.js
Ecmascript6Rumen/js/epub.min.map
Ecmascript6Rumen/js/hooks.min.js
Ecmascript6Rumen/js/hooks.min.map
Ecmascript6Rumen/js/reader.js
Ecmascript6Rumen/js/reader.js.map
Ecmascript6Rumen/js/reader.min.js
Ecmascript6Rumen/js/reader.min.map
Ecmascript6Rumen/js/hooks/__init__.py
Ecmascript6Rumen/js/hooks/extensions/__init__.py
Ecmascript6Rumen/js/hooks/extensions/highlight.js
Ecmascript6Rumen/js/libs/__init__.py
Ecmascript6Rumen/js/libs/jquery.min.js
Ecmascript6Rumen/js/libs/localforage.min.js
Ecmascript6Rumen/js/libs/screenfull.js
Ecmascript6Rumen/js/libs/screenfull.min.js
Ecmascript6Rumen/js/libs/zip.min.js
Ecmascript6Rumen/js/plugins/__init__.py
Ecmascript6Rumen/js/plugins/hypothesis.js
Ecmascript6Rumen/js/plugins/search.js
ecmascript_6_rumen-2024.3.1.0.dist-info/METADATA
ecmascript_6_rumen-2024.3.1.0.dist-info/WHEEL
ecmascript_6_rumen-2024.3.1.0.dist-info/entry_points.txt
ecmascript_6_rumen-2024.3.1.0.dist-info/top_level.txt
ecmascript_6_rumen-2024.3.1.0.dist-info/RECORD
